{
  "id": "the-longest-mile",
  "name": "the-longest-mile",
  "title": "The Longest Mile",
  "description": "Custom content for The Longest Mile campaign.",
  "compatibility": {
    "verified": "10",
    "maximum": "10"
  },
  "authors": [
    {
      "name": "Erin & Viv"
    }
  ],
  "packs": [
    {
      "name": "dervish",
      "label": "Dervish Archetype",
      "path": "/packs/dervish.db",
      "entity": "Item",
      "type": "Item",
      "system": "pf2e"
    },
    {
      "name": "deities",
      "label": "Deities",
      "path": "/packs/deities.db",
      "entity": "Item",
      "type": "Item",
      "system": "pf2e"
    },
    {
      "name": "spells",
      "label": "Spells",
      "path": "/packs/spells.db",
      "entity": "Item",
      "type": "Item",
      "system": "pf2e"
    },
    {
      "name": "feats",
      "label": "Custom Feats",
      "path": "/packs/feats.db",
      "entity": "Item",
      "type": "Item",
      "system": "pf2e"
    }
  ],
  "esmodules": [
    "scripts/character-sheet.js",
    "scripts/custom-buttons.js"
  ],
  "url": "https://github.com/cuyima/the-longest-mile",
  "download": "https://github.com/cuyima/the-longest-mile/releases/download/_VERSION/module.zip",
  "manifest": "https://github.com/cuyima/the-longest-mile/releases/latest/download/module.json",
  "version": "_VERSION"
}
